jwt_tui/__about__.py
jwt_tui/__init__.py
jwt_tui/entry_points.py
jwt_tui/main.py
jwt_tui/style.css
jwt_tui-1.0.4.dist-info/METADATA
jwt_tui-1.0.4.dist-info/WHEEL
jwt_tui-1.0.4.dist-info/entry_points.txt
jwt_tui-1.0.4.dist-info/RECORD
