Metadata-Version: 2.3
Name: jwt-tui
Version: 1.0.4
Summary: A TUI application for quickly decoding JWT to see the headers and payload.
Author-email: vikbytes <55359319+vikbytes@users.noreply.github.com>
License-Expression: MIT
Classifier: Operating System :: OS Independent
Classifier: Programming Language :: Python :: 3
Requires-Python: >=3.8
Requires-Dist: pyjwt==2.8.0
Requires-Dist: pyperclip==1.8.2
Requires-Dist: textual==0.48.1
